SCR/multiplier4b.v
module multiplier(
    input  wire       init,    // señal de inicio (nivel o pulso) tratada síncronamente
    input  wire       clk,
    input  wire       rst,     // reset síncrono, activo 1
    input  wire [2:0] MD,      // multiplicando (3 bits)
    input  wire [2:0] MR,      // multiplicador (3 bits)
    output reg  [5:0] PP,      // producto parcial / resultado (6 bits)
    output reg        done
    );

    // Estados
    localparam [2:0] START     = 3'b000;
    localparam [2:0] CHECK     = 3'b001;
    localparam [2:0] ADD       = 3'b010;
    localparam [2:0] SHIFT     = 3'b011;
    localparam [2:0] END_STATE = 3'b100;

    reg [2:0] fsm_state;
    reg [2:0] next_state;

    reg [5:0] A;        // acumulador desplazable (A << 1 cada SHIFT)
    reg [2:0] B;        // multiplicador (se desplaza a la derecha)
    reg [1:0] iter;     // cuenta 0..2 (3 iteraciones)

    wire LSB_B = B[0];

    // Lógica combinacional de transición (NO considera init aquí;
    // el reinicio/arranque por init se maneja síncronamente)
    always @(*) begin
        next_state = fsm_state; // default
        case (fsm_state)
            START:     next_state = START; // permanecer en START hasta que se pulse init (síncrono)
            CHECK:     next_state = (LSB_B == 1'b1) ? ADD : SHIFT;
            ADD:       next_state = SHIFT;
            SHIFT:     next_state = (iter == 2'd2) ? END_STATE : CHECK;
            END_STATE: next_state = END_STATE;
            default:   next_state = START;
        endcase
    end

    // Lógica secuencial: reset síncrono y prioridad síncrona a init
    always @(posedge clk) begin
        if (rst) begin
            // reset síncrono: dejar todo en estado inicial
            fsm_state <= START;
            PP        <= 6'd0;
            A         <= 6'd0;
            B         <= 3'd0;
            iter      <= 2'd0;
            done      <= 1'b0;
        end else if (init) begin
            // Opción B: FORZAR reinicio/recarga síncrona en el siguiente flanco de reloj.
            // Colocamos la FSM en CHECK para comenzar la ejecución inmediatamente.
            fsm_state <= CHECK;
            PP        <= 6'd0;
            A         <= {3'b000, MD}; // A inicia con MD en los bits bajos
            B         <= MR;
            iter      <= 2'd0;
            done      <= 1'b0;
        end else begin
            // comportamiento normal
            fsm_state <= next_state;

            case (fsm_state)
                START: begin
                    // en esta versión START se usa principalmente después de reset;
                    // no hacemos carga aquí porque init lo maneja síncronamente.
                    done <= 1'b0;
                end

                CHECK: begin
                    // decisión en combinacional; aquí no hay asignaciones específicas.
                    // dejamos las señales tal como están.
                end

                ADD: begin
                    // sumar A (6 bits) a PP
                    PP <= PP + A;
                end

                SHIFT: begin
                    // desplazar A a la izquierda (multiplica por 2) y B a la derecha
                    A    <= A << 1;
                    B    <= B >> 1;
                    iter <= iter + 2'd1;
                end

                END_STATE: begin
                    // indicar final; done se mantiene hasta que se pulse init o rst
                    done <= 1'b1;
                end

                default: begin
                    // seguridad: no hacer nada
                end
            endcase
        end
    end

endmodule

SCR/multiplier4b_tb.v
`include "multiplier4b.v"
`timescale 1ps/1ps

module multiplier_tb();

    reg        clk_tb;
    reg        rst_tb;
    reg        init_tb;
    reg  [2:0] MD_tb;
    reg  [2:0] MR_tb;
    wire [5:0] PP_tb;
    wire       done_tb;

    initial clk_tb = 1'b0;
    always  #5 clk_tb = ~clk_tb;

    multiplier uut (
        .init(init_tb),
        .clk (clk_tb),
        .rst (rst_tb),
        .MD  (MD_tb),
        .MR  (MR_tb),
        .PP  (PP_tb),
        .done(done_tb)
    );

    initial begin: TEST_CASE
        $dumpfile("multiplier_tb.vcd");
        $dumpvars(0, multiplier_tb); 
    end


    initial begin
        $display("\n=== multiplier_tb: traza por ciclo ===");
        $display("time(ps) | MD MR |  PP  |    A    B  iter | done | state");
        $display("--------------------------------------------------------");
    end

    always @(posedge clk_tb) begin
        $display("%8t |  %0d  %0d | %3d  | %3d %3d   %0d  |  %b   | %b",
                 $time,
                 MD_tb, MR_tb,
                 PP_tb,
                 uut.A, uut.B, uut.iter,
                 done_tb,
                 uut.fsm_state);
    end

    // tarea para ejecutar un caso de prueba con timeout (en ciclos de reloj)
    task run_case(input [2:0] multiplicando, input [2:0] multiplicador, input [5:0] esperado);
        integer timeout;
        begin
            // colocar operandos
            MD_tb = multiplicando;
            MR_tb = multiplicador;

            // esperar estabilidad (menos que un periodo)
            #2;

            // aplicar init síncrono: pulso de 1 ciclo
            @(posedge clk_tb);
            init_tb = 1'b1;
            @(posedge clk_tb);
            init_tb = 1'b0;

            // esperar done con timeout (ej: 40 ciclos)
            timeout = 0;
            while (!done_tb && timeout < 40) begin
                @(posedge clk_tb);
                timeout = timeout + 1;
            end

            // verificar resultado
            if (!done_tb) begin
                $display("[%0t ps] TIMEOUT: %0d x %0d -> PP=%0d (esperado %0d)",
                         $time, multiplicando, multiplicador, PP_tb, esperado);
            end else begin
                if (PP_tb === esperado) begin
                    $display("[%0t ps] PASS: %0d x %0d -> PP=%0d (esperado %0d)",
                             $time, multiplicando, multiplicador, PP_tb, esperado);
                end else begin
                    $display("[%0t ps] FAIL: %0d x %0d -> PP=%0d (esperado %0d)",
                             $time, multiplicando, multiplicador, PP_tb, esperado);
                end
            end

            // small gap before next case
            repeat (2) @(posedge clk_tb);
        end
    endtask

    // Secuencia principal de tests
    initial begin
        // Inicialización
        init_tb = 1'b0;
        MD_tb   = 3'd0;
        MR_tb   = 3'd0;
        rst_tb  = 1'b1;   // aplicar reset síncrono al inicio

        // Mantener rst activo unos ciclos
        repeat (3) @(posedge clk_tb);
        @(posedge clk_tb);
        rst_tb = 1'b0;    // liberar reset
        @(posedge clk_tb);

        $display("\n=== Inicio de tests ===");

        // Tests (multiplicando x multiplicador) -> esperado
        // Test 1: 5 x 3 = 15
        run_case(3'd5, 3'd3, 6'd15);

        // Test 2: 7 x 7 = 49
        run_case(3'd7, 3'd7, 6'd49);

        // Test 3: 6 x 2 = 12
        run_case(3'd6, 3'd2, 6'd12);

        // Test 4: 0 x 7 = 0
        run_case(3'd0, 3'd7, 6'd0);

        $display("=== Fin de tests ===");
        #50;

        $finish;
    end

endmodule

SCR/multiplier_tb.vcd
$date
	Sat Oct  4 18:15:22 2025
$end
$version
	Icarus Verilog
$end
$timescale
	1ps
$end
$scope module multiplier_tb $end
$var wire 1 ! done_tb $end
$var wire 6 " PP_tb [5:0] $end
$var reg 3 # MD_tb [2:0] $end
$var reg 3 $ MR_tb [2:0] $end
$var reg 1 % clk_tb $end
$var reg 1 & init_tb $end
$var reg 1 ' rst_tb $end
$scope module uut $end
$var wire 3 ( MD [2:0] $end
$var wire 3 ) MR [2:0] $end
$var wire 1 % clk $end
$var wire 1 & init $end
$var wire 1 ' rst $end
$var wire 1 * LSB_B $end
$var parameter 3 + ADD $end
$var parameter 3 , CHECK $end
$var parameter 3 - END_STATE $end
$var parameter 3 . SHIFT $end
$var parameter 3 / START $end
$var reg 6 0 A [5:0] $end
$var reg 3 1 B [2:0] $end
$var reg 6 2 PP [5:0] $end
$var reg 1 ! done $end
$var reg 3 3 fsm_state [2:0] $end
$var reg 2 4 iter [1:0] $end
$var reg 3 5 next_state [2:0] $end
$upscope $end
$scope begin TEST_CASE $end
$upscope $end
$scope task run_case $end
$var reg 6 6 esperado [5:0] $end
$var reg 3 7 multiplicador [2:0] $end
$var reg 3 8 multiplicando [2:0] $end
$var integer 32 9 timeout [31:0] $end
$upscope $end
$upscope $end
$enddefinitions $end
$comment Show the parameter values. $end
$dumpall
b0 /
b11 .
b100 -
b1 ,
b10 +
$end
#0
$dumpvars
bx 9
bx 8
bx 7
bx 6
bx 5
bx 4
bx 3
bx 2
bx 1
bx 0
x*
b0 )
b0 (
1'
0&
0%
b0 $
b0 #
bx "
x!
$end
#5
0*
b0 5
0!
b0 4
b0 1
b0 0
b0 "
b0 2
b0 3
1%
#10
0%
#15
1%
#20
0%
#25
1%
#30
0%
#35
0'
1%
#40
0%
#45
b11 $
b11 )
b101 #
b101 (
b1111 6
b11 7
b101 8
1%
#50
0%
#55
1*
b10 5
b11 1
b101 0
b1 3
1&
1%
#60
0%
#65
b0 9
0&
1%
#70
0%
#75
b11 5
b10 3
b1 9
1%
#80
0%
#85
b1 5
b101 "
b101 2
b11 3
b10 9
1%
#90
0%
#95
b10 5
b1 4
b1 1
b1010 0
b1 3
b11 9
1%
#100
0%
#105
b11 5
b10 3
b100 9
1%
#110
0%
#115
b1 5
b1111 "
b1111 2
b11 3
b101 9
1%
#120
0%
#125
0*
b11 5
b10 4
b0 1
b10100 0
b1 3
b110 9
1%
#130
0%
#135
b100 5
b11 3
b111 9
1%
#140
0%
#145
b11 4
b101000 0
b100 3
b1000 9
1%
#150
0%
#155
1!
b1001 9
1%
#160
0%
#165
b1010 9
1%
#170
0%
#175
1%
#180
0%
#185
b111 $
b111 )
b111 #
b111 (
b110001 6
b111 7
b111 8
1%
#190
0%
#195
1*
b10 5
0!
b0 4
b111 1
b111 0
b0 "
b0 2
b1 3
1&
1%
#200
0%
#205
b0 9
0&
1%
#210
0%
#215
b11 5
b10 3
b1 9
1%
#220
0%
#225
b1 5
b111 "
b111 2
b11 3
b10 9
1%
#230
0%
#235
b10 5
b1 4
b11 1
b1110 0
b1 3
b11 9
1%
#240
0%
#245
b11 5
b10 3
b100 9
1%
#250
0%
#255
b1 5
b10101 "
b10101 2
b11 3
b101 9
1%
#260
0%
#265
b10 5
b10 4
b1 1
b11100 0
b1 3
b110 9
1%
#270
0%
#275
b11 5
b10 3
b111 9
1%
#280
0%
#285
b100 5
b110001 "
b110001 2
b11 3
b1000 9
1%
#290
0%
#295
0*
b11 4
b0 1
b111000 0
b100 3
b1001 9
1%
#300
0%
#305
1!
b1010 9
1%
#310
0%
#315
b1011 9
1%
#320
0%
#325
1%
#330
0%
#335
b10 $
b10 )
b110 #
b110 (
b1100 6
b10 7
b110 8
1%
#340
0%
#345
b11 5
0!
b0 4
b10 1
b110 0
b0 "
b0 2
b1 3
1&
1%
#350
0%
#355
b0 9
0&
1%
#360
0%
#365
b1 5
b11 3
b1 9
1%
#370
0%
#375
1*
b10 5
b1 4
b1 1
b1100 0
b1 3
b10 9
1%
#380
0%
#385
b11 5
b10 3
b11 9
1%
#390
0%
#395
b1 5
b1100 "
b1100 2
b11 3
b100 9
1%
#400
0%
#405
0*
b11 5
b10 4
b0 1
b11000 0
b1 3
b101 9
1%
#410
0%
#415
b100 5
b11 3
b110 9
1%
#420
0%
#425
b11 4
b110000 0
b100 3
b111 9
1%
#430
0%
#435
1!
b1000 9
1%
#440
0%
#445
b1001 9
1%
#450
0%
#455
1%
#460
0%
#465
b111 $
b111 )
b0 #
b0 (
b0 6
b111 7
b0 8
1%
#470
0%
#475
1*
b10 5
0!
b0 4
b111 1
b0 0
b0 "
b0 2
b1 3
1&
1%
#480
0%
#485
b0 9
0&
1%
#490
0%
#495
b11 5
b10 3
b1 9
1%
#500
0%
#505
b1 5
b11 3
b10 9
1%
#510
0%
#515
b10 5
b1 4
b11 1
b1 3
b11 9
1%
#520
0%
#525
b11 5
b10 3
b100 9
1%
#530
0%
#535
b1 5
b11 3
b101 9
1%
#540
0%
#545
b10 5
b10 4
b1 1
b1 3
b110 9
1%
#550
0%
#555
b11 5
b10 3
b111 9
1%
#560
0%
#565
b100 5
b11 3
b1000 9
1%
#570
0%
#575
0*
b11 4
b0 1
b100 3
b1001 9
1%
#580
0%
#585
1!
b1010 9
1%
#590
0%
#595
b1011 9
1%
